[
  {
    "id": "61da02af-1b1b-45ea-8c46-e73276d0ed1b",
    "data": [
      {
        "text": "kontak ",
        "userDefined": false
      },
      {
        "text": "Pemadam Kebakaran kota Bekasi",
        "meta": "@sys.location",
        "alias": "location",
        "userDefined": false
      }
    ],
    "isTemplate": false,
    "count": 0,
    "lang": "id",
    "updated": 0
  },
  {
    "id": "f0ee8ebe-220e-4585-9fc8-f78d62e86801",
    "data": [
      {
        "text": "Pemadam Kebakaran kota Bekasi",
        "meta": "@sys.location",
        "alias": "location",
        "userDefined": false
      }
    ],
    "isTemplate": false,
    "count": 0,
    "lang": "id",
    "updated": 0
  },
  {
    "id": "62ff089c-9912-4eb5-aa32-2427055ccfb9",
    "data": [
      {
        "text": "Pemadam Kebakaran",
        "meta": "@sys.location",
        "alias": "location",
        "userDefined": false
      }
    ],
    "isTemplate": false,
    "count": 0,
    "lang": "id",
    "updated": 0
  }
]