[
  {
    "id": "599bd854-5d28-4e06-8f39-41ea8fa31a9e",
    "data": [
      {
        "text": "kontak Bencana ",
        "userDefined": false
      },
      {
        "text": "Alam",
        "userDefined": false
      },
      {
        "text": " ",
        "userDefined": false
      },
      {
        "text": "kota depok",
        "meta": "@sys.location",
        "alias": "location",
        "userDefined": false
      }
    ],
    "isTemplate": false,
    "count": 0,
    "lang": "id",
    "updated": 0
  },
  {
    "id": "d1bd5852-b26c-4554-9dad-edb88a46485a",
    "data": [
      {
        "text": "Bencana ",
        "userDefined": false
      },
      {
        "text": "Alam",
        "userDefined": false
      },
      {
        "text": " ",
        "userDefined": false
      },
      {
        "text": "kota depok",
        "meta": "@sys.location",
        "alias": "location",
        "userDefined": false
      }
    ],
    "isTemplate": false,
    "count": 0,
    "lang": "id",
    "updated": 0
  },
  {
    "id": "15c86cfb-8d5c-4a19-9fd5-726ba9fe2d05",
    "data": [
      {
        "text": "Bencana ",
        "userDefined": false
      },
      {
        "text": "Alam",
        "userDefined": false
      }
    ],
    "isTemplate": false,
    "count": 0,
    "lang": "id",
    "updated": 0
  }
]